flask_bootnav/__init__.py
flask_bootnav/elements.py
flask_bootnav/renderers.py
flask_bootnav-0.7.1.dist-info/DESCRIPTION.rst
flask_bootnav-0.7.1.dist-info/METADATA
flask_bootnav-0.7.1.dist-info/RECORD
flask_bootnav-0.7.1.dist-info/WHEEL
flask_bootnav-0.7.1.dist-info/metadata.json
flask_bootnav-0.7.1.dist-info/top_level.txt
