Metadata-Version: 2.0
Name: flask-bootnav
Version: 0.7.1
Summary: Easily create navigation for Flask applications.
Home-page: UNKNOWN
Author: UNKNOWN
Author-email: UNKNOWN
License: MIT
Platform: UNKNOWN
Classifier: Programming Language :: Python :: 2
Classifier: Programming Language :: Python :: 3
Requires-Dist: dominate
Requires-Dist: flask
Requires-Dist: visitor
